{"seed":521694690,"processedDockerfileHash":"bfb4a1b380968e7c93241aab6a35fb8e","fixedSmells":["use-no-install-recommends","do-not-use-apt-get-update-alone","pin-package-manager-versions-apt-get","pin-package-manager-versions-pip","pin-package-manager-versions-npm","pin-package-manager-versions-gem","pin-package-manager-versions-apk","use-copy-instead-of-add","use-wget-instead-of-add","do-not-have-secrets","have-a-healthcheck","have-a-user"],"successfullyFixedSmells":["have-a-healthcheck","have-a-user"],"processedDockerfile":"ARG RESTY_IMAGE_BASE=\"ubuntu\"\nARG RESTY_IMAGE_TAG=\"xenial\"\nFROM ${RESTY_IMAGE_BASE}:${RESTY_IMAGE_TAG}\nLABEL maintainer=\"Yu Gan <yg397@cornell.edu>\"\n#   Docker Build Arguments\nARG RESTY_VERSION=\"1.15.8.1rc1\"\nARG RESTY_LUAROCKS_VERSION=\"2.4.4\"\nARG RESTY_OPENSSL_VERSION=\"1.1.0j\"\nARG RESTY_PCRE_VERSION=\"8.42\"\nARG JAEGER_TRACING_VERSION=\"0.4.2\"\nARG NGINX_OPENTRACING_VERSION=\"0.8.0\"\nARG OPENTRACING_CPP_VERSION=\"1.5.1\"\nARG RESTY_J=\"1\"\nARG NUM_CPUS=\"40\"\nARG RESTY_CONFIG_OPTIONS=\" --with-file-aio  --with-http_addition_module  --with-http_auth_request_module  --with-http_dav_module  --with-http_flv_module  --with-http_geoip_module=dynamic  --with-http_gunzip_module  --with-http_gzip_static_module  --with-http_image_filter_module=dynamic  --with-http_mp4_module  --with-http_random_index_module  --with-http_realip_module  --with-http_secure_link_module  --with-http_slice_module  --with-http_ssl_module  --with-http_stub_status_module  --with-http_sub_module  --with-http_v2_module  --with-http_xslt_module=dynamic  --with-ipv6  --with-mail  --with-mail_ssl_module  --with-md5-asm  --with-pcre-jit  --with-sha1-asm  --with-stream  --with-stream_ssl_module  --with-threads  --add-dynamic-module=/usr/local/nginx-opentracing-${NGINX_OPENTRACING_VERSION}/opentracing  \"\nARG RESTY_CONFIG_OPTIONS_MORE=\"\"\nARG RESTY_ADD_PACKAGE_BUILDDEPS=\"\"\nARG RESTY_ADD_PACKAGE_RUNDEPS=\"\"\nARG RESTY_EVAL_PRE_CONFIGURE=\"\"\nARG RESTY_EVAL_POST_MAKE=\"\"\nLABEL resty_version=\"${RESTY_VERSION}\"\nLABEL resty_luarocks_version=\"${RESTY_LUAROCKS_VERSION}\"\nLABEL resty_openssl_version=\"${RESTY_OPENSSL_VERSION}\"\nLABEL resty_pcre_version=\"${RESTY_PCRE_VERSION}\"\nLABEL resty_config_options=\"${RESTY_CONFIG_OPTIONS}\"\nLABEL resty_config_options_more=\"${RESTY_CONFIG_OPTIONS_MORE}\"\nLABEL resty_add_package_builddeps=\"${RESTY_ADD_PACKAGE_BUILDDEPS}\"\nLABEL resty_add_package_rundeps=\"${RESTY_ADD_PACKAGE_RUNDEPS}\"\nLABEL resty_eval_pre_configure=\"${RESTY_EVAL_PRE_CONFIGURE}\"\nLABEL resty_eval_post_make=\"${RESTY_EVAL_POST_MAKE}\"\n#   These are not intended to be user-specified\nARG _RESTY_CONFIG_DEPS=\"--with-openssl=/tmp/openssl-${RESTY_OPENSSL_VERSION} --with-pcre=/tmp/pcre-${RESTY_PCRE_VERSION}\"\n#   1) Install apt dependencies\n#   2) Download and untar OpenSSL, PCRE, and OpenResty\n#   3) Build OpenResty\n#   4) Cleanup\nRUN DEBIAN_FRONTEND=noninteractive apt-get update \\\n && DEBIAN_FRONTEND=noninteractive apt-get install -y --no-install-recommends build-essential ca-certificates curl git gettext-base libgd-dev libgeoip-dev libncurses5-dev libperl-dev libreadline-dev libxslt1-dev make perl unzip zlib1g-dev cmake ${RESTY_ADD_PACKAGE_BUILDDEPS} ${RESTY_ADD_PACKAGE_RUNDEPS} \\\n && cd /tmp \\\n && if [ -n \"${RESTY_EVAL_PRE_CONFIGURE}\" ] ; then eval $( echo ${RESTY_EVAL_PRE_CONFIGURE} ;) ; fi \\\n && curl -fSL https://www.openssl.org/source/openssl-${RESTY_OPENSSL_VERSION}.tar.gz -o openssl-${RESTY_OPENSSL_VERSION}.tar.gz \\\n && tar xzf openssl-${RESTY_OPENSSL_VERSION}.tar.gz \\\n && curl -fSL https://ftp.pcre.org/pub/pcre/pcre-${RESTY_PCRE_VERSION}.tar.gz -o pcre-${RESTY_PCRE_VERSION}.tar.gz \\\n && tar xzf pcre-${RESTY_PCRE_VERSION}.tar.gz \\\n && cd /tmp \\\n && curl -fSL https://github.com/opentracing/opentracing-cpp/archive/v${OPENTRACING_CPP_VERSION}.tar.gz -o opentracing-cpp-${OPENTRACING_CPP_VERSION}.tar.gz \\\n && tar -zxf opentracing-cpp-${OPENTRACING_CPP_VERSION}.tar.gz \\\n && cd opentracing-cpp-${OPENTRACING_CPP_VERSION} \\\n && mkdir -p cmake-build \\\n && cd cmake-build \\\n && cmake -DCMAKE_BUILD_TYPE=Release -DBUILD_MOCKTRACER=OFF -DBUILD_STATIC_LIBS=OFF -DBUILD_TESTING=OFF .. \\\n && make -j${NUM_CPUS} \\\n && make -j${NUM_CPUS} install \\\n && cd /tmp \\\n && rm -rf opentracing-cpp-${OPENTRACING_CPP_VERSION}.tar.gz opentracing-cpp-${OPENTRACING_CPP_VERSION} \\\n && cd /tmp \\\n && git clone https://github.com/jkeys089/lua-resty-hmac.git \\\n && cd lua-resty-hmac \\\n && make \\\n && make install \\\n && cd /tmp \\\n && rm -rf lua-resty-hmac \\\n && cd /usr/local/lib \\\n && curl -fSL https://github.com/jaegertracing/jaeger-client-cpp/releases/download/v${JAEGER_TRACING_VERSION}/libjaegertracing_plugin.linux_amd64.so -o libjaegertracing_plugin.so\nRUN cd /usr/local \\\n && curl -fSL https://github.com/opentracing-contrib/nginx-opentracing/archive/v${NGINX_OPENTRACING_VERSION}.tar.gz -o nginx-opentracing-${NGINX_OPENTRACING_VERSION}.tar.gz \\\n && tar -zxf nginx-opentracing-${NGINX_OPENTRACING_VERSION}.tar.gz \\\n && rm nginx-opentracing-${NGINX_OPENTRACING_VERSION}.tar.gz \\\n && cd /tmp \\\n && curl -fSL https://openresty.org/download/openresty-${RESTY_VERSION}.tar.gz -o openresty-${RESTY_VERSION}.tar.gz \\\n && tar xzf openresty-${RESTY_VERSION}.tar.gz \\\n && cd /tmp/openresty-${RESTY_VERSION} \\\n && ./configure -j${RESTY_J} ${_RESTY_CONFIG_DEPS} ${RESTY_CONFIG_OPTIONS} ${RESTY_CONFIG_OPTIONS_MORE} \\\n && make -j${RESTY_J} \\\n && make -j${RESTY_J} install \\\n && cd /tmp \\\n && rm -rf openssl-${RESTY_OPENSSL_VERSION} openssl-${RESTY_OPENSSL_VERSION}.tar.gz openresty-${RESTY_VERSION}.tar.gz openresty-${RESTY_VERSION} pcre-${RESTY_PCRE_VERSION}.tar.gz pcre-${RESTY_PCRE_VERSION}\nRUN cd /tmp \\\n && curl -fSL https://github.com/luarocks/luarocks/archive/${RESTY_LUAROCKS_VERSION}.tar.gz -o luarocks-${RESTY_LUAROCKS_VERSION}.tar.gz \\\n && tar xzf luarocks-${RESTY_LUAROCKS_VERSION}.tar.gz \\\n && cd luarocks-${RESTY_LUAROCKS_VERSION} \\\n && ./configure --prefix=/usr/local/openresty/luajit --with-lua=/usr/local/openresty/luajit --lua-suffix=jit-2.1.0-beta3 --with-lua-include=/usr/local/openresty/luajit/include/luajit-2.1 \\\n && make build \\\n && make install \\\n && cd /tmp \\\n && if [ -n \"${RESTY_EVAL_POST_MAKE}\" ] ; then eval $( echo ${RESTY_EVAL_POST_MAKE} ;) ; fi \\\n && rm -rf luarocks-${RESTY_LUAROCKS_VERSION} luarocks-${RESTY_LUAROCKS_VERSION}.tar.gz \\\n && if [ -n \"${RESTY_ADD_PACKAGE_BUILDDEPS}\" ] ; then DEBIAN_FRONTEND=noninteractive apt-get remove --purge \"${RESTY_ADD_PACKAGE_BUILDDEPS}\" ; fi \\\n && DEBIAN_FRONTEND=noninteractive apt-get autoremove -y \\\n && ln -sf /dev/stdout /usr/local/openresty/nginx/logs/access.log \\\n && ln -sf /dev/stderr /usr/local/openresty/nginx/logs/error.log\n#   Add additional binaries into PATH for convenience\nENV PATH=\"$PATH:/usr/local/openresty/luajit/bin:/usr/local/openresty/nginx/sbin:/usr/local/openresty/bin\"\n#   Add LuaRocks paths\n#   If OpenResty changes, these may need updating:\n#      /usr/local/openresty/bin/resty -e 'print(package.path)'\n#      /usr/local/openresty/bin/resty -e 'print(package.cpath)'\nENV LUA_PATH=\"/usr/local/openresty/site/lualib/?.ljbc;/usr/local/openresty/site/lualib/?/init.ljbc;/usr/local/openresty/lualib/?.ljbc;/usr/local/openresty/lualib/?/init.ljbc;/usr/local/openresty/site/lualib/?.lua;/usr/local/openresty/site/lualib/?/init.lua;/usr/local/openresty/lualib/?.lua;/usr/local/openresty/lualib/?/init.lua;./?.lua;/usr/local/openresty/luajit/share/luajit-2.1.0-beta3/?.lua;/usr/local/share/lua/5.1/?.lua;/usr/local/share/lua/5.1/?/init.lua;/usr/local/openresty/luajit/share/lua/5.1/?.lua;/usr/local/openresty/luajit/share/lua/5.1/?/init.lua;/usr/local/openresty/lualib/?/?.lua;/usr/local/openresty/lualib/thrift/?.lua\"\nENV LUA_CPATH=\"/usr/local/openresty/site/lualib/?.so;/usr/local/openresty/lualib/?.so;./?.so;/usr/local/lib/lua/5.1/?.so;/usr/local/openresty/luajit/lib/lua/5.1/?.so;/usr/local/lib/lua/5.1/loadall.so;/usr/local/openresty/luajit/lib/lua/5.1/?.so;/usr/local/openresty/lualib/?/?.so\"\nCOPY lua-thrift /usr/local/openresty/lualib/thrift\nCOPY lua-bridge-tracer /tmp/lua-bridge-tracer\nCOPY lua-json/json.lua /usr/local/openresty/lualib/json/json.lua\nRUN cd /usr/local/openresty/lualib/thrift/src \\\n && make \\\n && make install \\\n && cd /tmp/lua-bridge-tracer \\\n && mkdir -p cmake-build \\\n && cd cmake-build \\\n && cmake -DCMAKE_BUILD_TYPE=Release .. \\\n && make -j${NUM_CPUS} \\\n && make -j${NUM_CPUS} install\n#      && cd /tmp\n#      && rm -rf lua-bridge-tracer\nENV LUA_PATH=\"$LUA_PATH;/gen-lua/?.lua\"\nRUN luarocks install long \\\n && luarocks install lua-resty-jwt \\\n && ldconfig\n#   Copy nginx configuration files\nCOPY nginx.conf /usr/local/openresty/nginx/conf/nginx.conf\nCOPY nginx.vh.default.conf /etc/nginx/conf.d/default.conf\nCMD [\"/usr/local/openresty/bin/openresty\", \"-g\", \"daemon\", \"off\"]\n#   Use SIGQUIT instead of default SIGTERM to cleanly drain requests\n#   See https://github.com/openresty/docker-openresty/blob/master/README.md#tips--pitfalls\nSTOPSIGNAL SIGQUIT\nRUN groupadd --system docker-user ; useradd --system --gid docker-user docker-user\nUSER docker-user\n# Please add your HEALTHCHECK here!!!\n","originalDockerfile":"ARG RESTY_IMAGE_BASE=\"ubuntu\"\nARG RESTY_IMAGE_TAG=\"xenial\"\nFROM ${RESTY_IMAGE_BASE}:${RESTY_IMAGE_TAG}\nLABEL maintainer=\"Yu Gan <yg397@cornell.edu>\"\n#  Docker Build Arguments\nARG RESTY_VERSION=\"1.15.8.1rc1\"\nARG RESTY_LUAROCKS_VERSION=\"2.4.4\"\nARG RESTY_OPENSSL_VERSION=\"1.1.0j\"\nARG RESTY_PCRE_VERSION=\"8.42\"\nARG JAEGER_TRACING_VERSION=\"0.4.2\"\nARG NGINX_OPENTRACING_VERSION=\"0.8.0\"\nARG OPENTRACING_CPP_VERSION=\"1.5.1\"\nARG RESTY_J=\"1\"\nARG NUM_CPUS=\"40\"\nARG RESTY_CONFIG_OPTIONS=\" --with-file-aio  --with-http_addition_module  --with-http_auth_request_module  --with-http_dav_module  --with-http_flv_module  --with-http_geoip_module=dynamic  --with-http_gunzip_module  --with-http_gzip_static_module  --with-http_image_filter_module=dynamic  --with-http_mp4_module  --with-http_random_index_module  --with-http_realip_module  --with-http_secure_link_module  --with-http_slice_module  --with-http_ssl_module  --with-http_stub_status_module  --with-http_sub_module  --with-http_v2_module  --with-http_xslt_module=dynamic  --with-ipv6  --with-mail  --with-mail_ssl_module  --with-md5-asm  --with-pcre-jit  --with-sha1-asm  --with-stream  --with-stream_ssl_module  --with-threads  --add-dynamic-module=/usr/local/nginx-opentracing-${NGINX_OPENTRACING_VERSION}/opentracing  \"\nARG RESTY_CONFIG_OPTIONS_MORE=\"\"\nARG RESTY_ADD_PACKAGE_BUILDDEPS=\"\"\nARG RESTY_ADD_PACKAGE_RUNDEPS=\"\"\nARG RESTY_EVAL_PRE_CONFIGURE=\"\"\nARG RESTY_EVAL_POST_MAKE=\"\"\nLABEL resty_version=\"${RESTY_VERSION}\"\nLABEL resty_luarocks_version=\"${RESTY_LUAROCKS_VERSION}\"\nLABEL resty_openssl_version=\"${RESTY_OPENSSL_VERSION}\"\nLABEL resty_pcre_version=\"${RESTY_PCRE_VERSION}\"\nLABEL resty_config_options=\"${RESTY_CONFIG_OPTIONS}\"\nLABEL resty_config_options_more=\"${RESTY_CONFIG_OPTIONS_MORE}\"\nLABEL resty_add_package_builddeps=\"${RESTY_ADD_PACKAGE_BUILDDEPS}\"\nLABEL resty_add_package_rundeps=\"${RESTY_ADD_PACKAGE_RUNDEPS}\"\nLABEL resty_eval_pre_configure=\"${RESTY_EVAL_PRE_CONFIGURE}\"\nLABEL resty_eval_post_make=\"${RESTY_EVAL_POST_MAKE}\"\n#  These are not intended to be user-specified\nARG _RESTY_CONFIG_DEPS=\"--with-openssl=/tmp/openssl-${RESTY_OPENSSL_VERSION} --with-pcre=/tmp/pcre-${RESTY_PCRE_VERSION}\"\n#  1) Install apt dependencies\n#  2) Download and untar OpenSSL, PCRE, and OpenResty\n#  3) Build OpenResty\n#  4) Cleanup\nRUN DEBIAN_FRONTEND=noninteractive apt-get update \\\n && DEBIAN_FRONTEND=noninteractive apt-get install -y --no-install-recommends build-essential ca-certificates curl git gettext-base libgd-dev libgeoip-dev libncurses5-dev libperl-dev libreadline-dev libxslt1-dev make perl unzip zlib1g-dev cmake ${RESTY_ADD_PACKAGE_BUILDDEPS} ${RESTY_ADD_PACKAGE_RUNDEPS} \\\n && cd /tmp \\\n && if [ -n \"${RESTY_EVAL_PRE_CONFIGURE}\" ] ; then eval $( echo ${RESTY_EVAL_PRE_CONFIGURE} ;) ; fi \\\n && curl -fSL https://www.openssl.org/source/openssl-${RESTY_OPENSSL_VERSION}.tar.gz -o openssl-${RESTY_OPENSSL_VERSION}.tar.gz \\\n && tar xzf openssl-${RESTY_OPENSSL_VERSION}.tar.gz \\\n && curl -fSL https://ftp.pcre.org/pub/pcre/pcre-${RESTY_PCRE_VERSION}.tar.gz -o pcre-${RESTY_PCRE_VERSION}.tar.gz \\\n && tar xzf pcre-${RESTY_PCRE_VERSION}.tar.gz \\\n && cd /tmp \\\n && curl -fSL https://github.com/opentracing/opentracing-cpp/archive/v${OPENTRACING_CPP_VERSION}.tar.gz -o opentracing-cpp-${OPENTRACING_CPP_VERSION}.tar.gz \\\n && tar -zxf opentracing-cpp-${OPENTRACING_CPP_VERSION}.tar.gz \\\n && cd opentracing-cpp-${OPENTRACING_CPP_VERSION} \\\n && mkdir -p cmake-build \\\n && cd cmake-build \\\n && cmake -DCMAKE_BUILD_TYPE=Release -DBUILD_MOCKTRACER=OFF -DBUILD_STATIC_LIBS=OFF -DBUILD_TESTING=OFF .. \\\n && make -j${NUM_CPUS} \\\n && make -j${NUM_CPUS} install \\\n && cd /tmp \\\n && rm -rf opentracing-cpp-${OPENTRACING_CPP_VERSION}.tar.gz opentracing-cpp-${OPENTRACING_CPP_VERSION} \\\n && cd /tmp \\\n && git clone https://github.com/jkeys089/lua-resty-hmac.git \\\n && cd lua-resty-hmac \\\n && make \\\n && make install \\\n && cd /tmp \\\n && rm -rf lua-resty-hmac \\\n && cd /usr/local/lib \\\n && curl -fSL https://github.com/jaegertracing/jaeger-client-cpp/releases/download/v${JAEGER_TRACING_VERSION}/libjaegertracing_plugin.linux_amd64.so -o libjaegertracing_plugin.so\nRUN cd /usr/local \\\n && curl -fSL https://github.com/opentracing-contrib/nginx-opentracing/archive/v${NGINX_OPENTRACING_VERSION}.tar.gz -o nginx-opentracing-${NGINX_OPENTRACING_VERSION}.tar.gz \\\n && tar -zxf nginx-opentracing-${NGINX_OPENTRACING_VERSION}.tar.gz \\\n && rm nginx-opentracing-${NGINX_OPENTRACING_VERSION}.tar.gz \\\n && cd /tmp \\\n && curl -fSL https://openresty.org/download/openresty-${RESTY_VERSION}.tar.gz -o openresty-${RESTY_VERSION}.tar.gz \\\n && tar xzf openresty-${RESTY_VERSION}.tar.gz \\\n && cd /tmp/openresty-${RESTY_VERSION} \\\n && ./configure -j${RESTY_J} ${_RESTY_CONFIG_DEPS} ${RESTY_CONFIG_OPTIONS} ${RESTY_CONFIG_OPTIONS_MORE} \\\n && make -j${RESTY_J} \\\n && make -j${RESTY_J} install \\\n && cd /tmp \\\n && rm -rf openssl-${RESTY_OPENSSL_VERSION} openssl-${RESTY_OPENSSL_VERSION}.tar.gz openresty-${RESTY_VERSION}.tar.gz openresty-${RESTY_VERSION} pcre-${RESTY_PCRE_VERSION}.tar.gz pcre-${RESTY_PCRE_VERSION}\nRUN cd /tmp \\\n && curl -fSL https://github.com/luarocks/luarocks/archive/${RESTY_LUAROCKS_VERSION}.tar.gz -o luarocks-${RESTY_LUAROCKS_VERSION}.tar.gz \\\n && tar xzf luarocks-${RESTY_LUAROCKS_VERSION}.tar.gz \\\n && cd luarocks-${RESTY_LUAROCKS_VERSION} \\\n && ./configure --prefix=/usr/local/openresty/luajit --with-lua=/usr/local/openresty/luajit --lua-suffix=jit-2.1.0-beta3 --with-lua-include=/usr/local/openresty/luajit/include/luajit-2.1 \\\n && make build \\\n && make install \\\n && cd /tmp \\\n && if [ -n \"${RESTY_EVAL_POST_MAKE}\" ] ; then eval $( echo ${RESTY_EVAL_POST_MAKE} ;) ; fi \\\n && rm -rf luarocks-${RESTY_LUAROCKS_VERSION} luarocks-${RESTY_LUAROCKS_VERSION}.tar.gz \\\n && if [ -n \"${RESTY_ADD_PACKAGE_BUILDDEPS}\" ] ; then DEBIAN_FRONTEND=noninteractive apt-get remove --purge \"${RESTY_ADD_PACKAGE_BUILDDEPS}\" ; fi \\\n && DEBIAN_FRONTEND=noninteractive apt-get autoremove -y \\\n && ln -sf /dev/stdout /usr/local/openresty/nginx/logs/access.log \\\n && ln -sf /dev/stderr /usr/local/openresty/nginx/logs/error.log\n#  Add additional binaries into PATH for convenience\nENV PATH=\"$PATH:/usr/local/openresty/luajit/bin:/usr/local/openresty/nginx/sbin:/usr/local/openresty/bin\"\n#  Add LuaRocks paths\n#  If OpenResty changes, these may need updating:\n#     /usr/local/openresty/bin/resty -e 'print(package.path)'\n#     /usr/local/openresty/bin/resty -e 'print(package.cpath)'\nENV LUA_PATH=\"/usr/local/openresty/site/lualib/?.ljbc;/usr/local/openresty/site/lualib/?/init.ljbc;/usr/local/openresty/lualib/?.ljbc;/usr/local/openresty/lualib/?/init.ljbc;/usr/local/openresty/site/lualib/?.lua;/usr/local/openresty/site/lualib/?/init.lua;/usr/local/openresty/lualib/?.lua;/usr/local/openresty/lualib/?/init.lua;./?.lua;/usr/local/openresty/luajit/share/luajit-2.1.0-beta3/?.lua;/usr/local/share/lua/5.1/?.lua;/usr/local/share/lua/5.1/?/init.lua;/usr/local/openresty/luajit/share/lua/5.1/?.lua;/usr/local/openresty/luajit/share/lua/5.1/?/init.lua;/usr/local/openresty/lualib/?/?.lua;/usr/local/openresty/lualib/thrift/?.lua\"\nENV LUA_CPATH=\"/usr/local/openresty/site/lualib/?.so;/usr/local/openresty/lualib/?.so;./?.so;/usr/local/lib/lua/5.1/?.so;/usr/local/openresty/luajit/lib/lua/5.1/?.so;/usr/local/lib/lua/5.1/loadall.so;/usr/local/openresty/luajit/lib/lua/5.1/?.so;/usr/local/openresty/lualib/?/?.so\"\nCOPY lua-thrift /usr/local/openresty/lualib/thrift\nCOPY lua-bridge-tracer /tmp/lua-bridge-tracer\nCOPY lua-json/json.lua /usr/local/openresty/lualib/json/json.lua\nRUN cd /usr/local/openresty/lualib/thrift/src \\\n && make \\\n && make install \\\n && cd /tmp/lua-bridge-tracer \\\n && mkdir -p cmake-build \\\n && cd cmake-build \\\n && cmake -DCMAKE_BUILD_TYPE=Release .. \\\n && make -j${NUM_CPUS} \\\n && make -j${NUM_CPUS} install\n#     && cd /tmp\n#     && rm -rf lua-bridge-tracer\nENV LUA_PATH=\"$LUA_PATH;/gen-lua/?.lua\"\nRUN luarocks install long \\\n && luarocks install lua-resty-jwt \\\n && ldconfig\n#  Copy nginx configuration files\nCOPY nginx.conf /usr/local/openresty/nginx/conf/nginx.conf\nCOPY nginx.vh.default.conf /etc/nginx/conf.d/default.conf\nCMD [\"/usr/local/openresty/bin/openresty\", \"-g\", \"daemon\", \"off\"]\n#  Use SIGQUIT instead of default SIGTERM to cleanly drain requests\n#  See https://github.com/openresty/docker-openresty/blob/master/README.md#tips--pitfalls\nSTOPSIGNAL SIGQUIT\n","injectedSmells":[],"originalDockerfileHash":"306908b69363849af991443c1f186de2","successfullyInjectedSmells":[],"originalDockerfileUglified":"ARG RESTY_IMAGE_BASE=\"ubuntu\"\nARG RESTY_IMAGE_TAG=\"xenial\"\nFROM ${RESTY_IMAGE_BASE}:${RESTY_IMAGE_TAG}\nLABEL maintainer=\"Yu Gan <yg397@cornell.edu>\"\n#   Docker Build Arguments\nARG RESTY_VERSION=\"1.15.8.1rc1\"\nARG RESTY_LUAROCKS_VERSION=\"2.4.4\"\nARG RESTY_OPENSSL_VERSION=\"1.1.0j\"\nARG RESTY_PCRE_VERSION=\"8.42\"\nARG JAEGER_TRACING_VERSION=\"0.4.2\"\nARG NGINX_OPENTRACING_VERSION=\"0.8.0\"\nARG OPENTRACING_CPP_VERSION=\"1.5.1\"\nARG RESTY_J=\"1\"\nARG NUM_CPUS=\"40\"\nARG RESTY_CONFIG_OPTIONS=\" --with-file-aio  --with-http_addition_module  --with-http_auth_request_module  --with-http_dav_module  --with-http_flv_module  --with-http_geoip_module=dynamic  --with-http_gunzip_module  --with-http_gzip_static_module  --with-http_image_filter_module=dynamic  --with-http_mp4_module  --with-http_random_index_module  --with-http_realip_module  --with-http_secure_link_module  --with-http_slice_module  --with-http_ssl_module  --with-http_stub_status_module  --with-http_sub_module  --with-http_v2_module  --with-http_xslt_module=dynamic  --with-ipv6  --with-mail  --with-mail_ssl_module  --with-md5-asm  --with-pcre-jit  --with-sha1-asm  --with-stream  --with-stream_ssl_module  --with-threads  --add-dynamic-module=/usr/local/nginx-opentracing-${NGINX_OPENTRACING_VERSION}/opentracing  \"\nARG RESTY_CONFIG_OPTIONS_MORE=\"\"\nARG RESTY_ADD_PACKAGE_BUILDDEPS=\"\"\nARG RESTY_ADD_PACKAGE_RUNDEPS=\"\"\nARG RESTY_EVAL_PRE_CONFIGURE=\"\"\nARG RESTY_EVAL_POST_MAKE=\"\"\nLABEL resty_version=\"${RESTY_VERSION}\"\nLABEL resty_luarocks_version=\"${RESTY_LUAROCKS_VERSION}\"\nLABEL resty_openssl_version=\"${RESTY_OPENSSL_VERSION}\"\nLABEL resty_pcre_version=\"${RESTY_PCRE_VERSION}\"\nLABEL resty_config_options=\"${RESTY_CONFIG_OPTIONS}\"\nLABEL resty_config_options_more=\"${RESTY_CONFIG_OPTIONS_MORE}\"\nLABEL resty_add_package_builddeps=\"${RESTY_ADD_PACKAGE_BUILDDEPS}\"\nLABEL resty_add_package_rundeps=\"${RESTY_ADD_PACKAGE_RUNDEPS}\"\nLABEL resty_eval_pre_configure=\"${RESTY_EVAL_PRE_CONFIGURE}\"\nLABEL resty_eval_post_make=\"${RESTY_EVAL_POST_MAKE}\"\n#   These are not intended to be user-specified\nARG _RESTY_CONFIG_DEPS=\"--with-openssl=/tmp/openssl-${RESTY_OPENSSL_VERSION} --with-pcre=/tmp/pcre-${RESTY_PCRE_VERSION}\"\n#   1) Install apt dependencies\n#   2) Download and untar OpenSSL, PCRE, and OpenResty\n#   3) Build OpenResty\n#   4) Cleanup\nRUN DEBIAN_FRONTEND=noninteractive apt-get update \\\n && DEBIAN_FRONTEND=noninteractive apt-get install -y --no-install-recommends build-essential ca-certificates curl git gettext-base libgd-dev libgeoip-dev libncurses5-dev libperl-dev libreadline-dev libxslt1-dev make perl unzip zlib1g-dev cmake ${RESTY_ADD_PACKAGE_BUILDDEPS} ${RESTY_ADD_PACKAGE_RUNDEPS} \\\n && cd /tmp \\\n && if [ -n \"${RESTY_EVAL_PRE_CONFIGURE}\" ] ; then eval $( echo ${RESTY_EVAL_PRE_CONFIGURE} ;) ; fi \\\n && curl -fSL https://www.openssl.org/source/openssl-${RESTY_OPENSSL_VERSION}.tar.gz -o openssl-${RESTY_OPENSSL_VERSION}.tar.gz \\\n && tar xzf openssl-${RESTY_OPENSSL_VERSION}.tar.gz \\\n && curl -fSL https://ftp.pcre.org/pub/pcre/pcre-${RESTY_PCRE_VERSION}.tar.gz -o pcre-${RESTY_PCRE_VERSION}.tar.gz \\\n && tar xzf pcre-${RESTY_PCRE_VERSION}.tar.gz \\\n && cd /tmp \\\n && curl -fSL https://github.com/opentracing/opentracing-cpp/archive/v${OPENTRACING_CPP_VERSION}.tar.gz -o opentracing-cpp-${OPENTRACING_CPP_VERSION}.tar.gz \\\n && tar -zxf opentracing-cpp-${OPENTRACING_CPP_VERSION}.tar.gz \\\n && cd opentracing-cpp-${OPENTRACING_CPP_VERSION} \\\n && mkdir -p cmake-build \\\n && cd cmake-build \\\n && cmake -DCMAKE_BUILD_TYPE=Release -DBUILD_MOCKTRACER=OFF -DBUILD_STATIC_LIBS=OFF -DBUILD_TESTING=OFF .. \\\n && make -j${NUM_CPUS} \\\n && make -j${NUM_CPUS} install \\\n && cd /tmp \\\n && rm -rf opentracing-cpp-${OPENTRACING_CPP_VERSION}.tar.gz opentracing-cpp-${OPENTRACING_CPP_VERSION} \\\n && cd /tmp \\\n && git clone https://github.com/jkeys089/lua-resty-hmac.git \\\n && cd lua-resty-hmac \\\n && make \\\n && make install \\\n && cd /tmp \\\n && rm -rf lua-resty-hmac \\\n && cd /usr/local/lib \\\n && curl -fSL https://github.com/jaegertracing/jaeger-client-cpp/releases/download/v${JAEGER_TRACING_VERSION}/libjaegertracing_plugin.linux_amd64.so -o libjaegertracing_plugin.so\nRUN cd /usr/local \\\n && curl -fSL https://github.com/opentracing-contrib/nginx-opentracing/archive/v${NGINX_OPENTRACING_VERSION}.tar.gz -o nginx-opentracing-${NGINX_OPENTRACING_VERSION}.tar.gz \\\n && tar -zxf nginx-opentracing-${NGINX_OPENTRACING_VERSION}.tar.gz \\\n && rm nginx-opentracing-${NGINX_OPENTRACING_VERSION}.tar.gz \\\n && cd /tmp \\\n && curl -fSL https://openresty.org/download/openresty-${RESTY_VERSION}.tar.gz -o openresty-${RESTY_VERSION}.tar.gz \\\n && tar xzf openresty-${RESTY_VERSION}.tar.gz \\\n && cd /tmp/openresty-${RESTY_VERSION} \\\n && ./configure -j${RESTY_J} ${_RESTY_CONFIG_DEPS} ${RESTY_CONFIG_OPTIONS} ${RESTY_CONFIG_OPTIONS_MORE} \\\n && make -j${RESTY_J} \\\n && make -j${RESTY_J} install \\\n && cd /tmp \\\n && rm -rf openssl-${RESTY_OPENSSL_VERSION} openssl-${RESTY_OPENSSL_VERSION}.tar.gz openresty-${RESTY_VERSION}.tar.gz openresty-${RESTY_VERSION} pcre-${RESTY_PCRE_VERSION}.tar.gz pcre-${RESTY_PCRE_VERSION}\nRUN cd /tmp \\\n && curl -fSL https://github.com/luarocks/luarocks/archive/${RESTY_LUAROCKS_VERSION}.tar.gz -o luarocks-${RESTY_LUAROCKS_VERSION}.tar.gz \\\n && tar xzf luarocks-${RESTY_LUAROCKS_VERSION}.tar.gz \\\n && cd luarocks-${RESTY_LUAROCKS_VERSION} \\\n && ./configure --prefix=/usr/local/openresty/luajit --with-lua=/usr/local/openresty/luajit --lua-suffix=jit-2.1.0-beta3 --with-lua-include=/usr/local/openresty/luajit/include/luajit-2.1 \\\n && make build \\\n && make install \\\n && cd /tmp \\\n && if [ -n \"${RESTY_EVAL_POST_MAKE}\" ] ; then eval $( echo ${RESTY_EVAL_POST_MAKE} ;) ; fi \\\n && rm -rf luarocks-${RESTY_LUAROCKS_VERSION} luarocks-${RESTY_LUAROCKS_VERSION}.tar.gz \\\n && if [ -n \"${RESTY_ADD_PACKAGE_BUILDDEPS}\" ] ; then DEBIAN_FRONTEND=noninteractive apt-get remove --purge \"${RESTY_ADD_PACKAGE_BUILDDEPS}\" ; fi \\\n && DEBIAN_FRONTEND=noninteractive apt-get autoremove -y \\\n && ln -sf /dev/stdout /usr/local/openresty/nginx/logs/access.log \\\n && ln -sf /dev/stderr /usr/local/openresty/nginx/logs/error.log\n#   Add additional binaries into PATH for convenience\nENV PATH=\"$PATH:/usr/local/openresty/luajit/bin:/usr/local/openresty/nginx/sbin:/usr/local/openresty/bin\"\n#   Add LuaRocks paths\n#   If OpenResty changes, these may need updating:\n#      /usr/local/openresty/bin/resty -e 'print(package.path)'\n#      /usr/local/openresty/bin/resty -e 'print(package.cpath)'\nENV LUA_PATH=\"/usr/local/openresty/site/lualib/?.ljbc;/usr/local/openresty/site/lualib/?/init.ljbc;/usr/local/openresty/lualib/?.ljbc;/usr/local/openresty/lualib/?/init.ljbc;/usr/local/openresty/site/lualib/?.lua;/usr/local/openresty/site/lualib/?/init.lua;/usr/local/openresty/lualib/?.lua;/usr/local/openresty/lualib/?/init.lua;./?.lua;/usr/local/openresty/luajit/share/luajit-2.1.0-beta3/?.lua;/usr/local/share/lua/5.1/?.lua;/usr/local/share/lua/5.1/?/init.lua;/usr/local/openresty/luajit/share/lua/5.1/?.lua;/usr/local/openresty/luajit/share/lua/5.1/?/init.lua;/usr/local/openresty/lualib/?/?.lua;/usr/local/openresty/lualib/thrift/?.lua\"\nENV LUA_CPATH=\"/usr/local/openresty/site/lualib/?.so;/usr/local/openresty/lualib/?.so;./?.so;/usr/local/lib/lua/5.1/?.so;/usr/local/openresty/luajit/lib/lua/5.1/?.so;/usr/local/lib/lua/5.1/loadall.so;/usr/local/openresty/luajit/lib/lua/5.1/?.so;/usr/local/openresty/lualib/?/?.so\"\nCOPY lua-thrift /usr/local/openresty/lualib/thrift\nCOPY lua-bridge-tracer /tmp/lua-bridge-tracer\nCOPY lua-json/json.lua /usr/local/openresty/lualib/json/json.lua\nRUN cd /usr/local/openresty/lualib/thrift/src \\\n && make \\\n && make install \\\n && cd /tmp/lua-bridge-tracer \\\n && mkdir -p cmake-build \\\n && cd cmake-build \\\n && cmake -DCMAKE_BUILD_TYPE=Release .. \\\n && make -j${NUM_CPUS} \\\n && make -j${NUM_CPUS} install\n#      && cd /tmp\n#      && rm -rf lua-bridge-tracer\nENV LUA_PATH=\"$LUA_PATH;/gen-lua/?.lua\"\nRUN luarocks install long \\\n && luarocks install lua-resty-jwt \\\n && ldconfig\n#   Copy nginx configuration files\nCOPY nginx.conf /usr/local/openresty/nginx/conf/nginx.conf\nCOPY nginx.vh.default.conf /etc/nginx/conf.d/default.conf\nCMD [\"/usr/local/openresty/bin/openresty\", \"-g\", \"daemon\", \"off\"]\n#   Use SIGQUIT instead of default SIGTERM to cleanly drain requests\n#   See https://github.com/openresty/docker-openresty/blob/master/README.md#tips--pitfalls\nSTOPSIGNAL SIGQUIT\n","originalDockerfileUglifiedHash":"3ce92758ff6130339dc56addfe953b62","fileName":"/ICSME-replicationpackage/dataset/smelly_dockerfiles_bianncle/851681afc43aacd67de2ce73c8f1cfe5f233830f.dockerfile"}