{"seed":1174258188,"processedDockerfileHash":"83b01f84e9413e12eb98f51125ac8675","fixedSmells":["use-no-install-recommends","do-not-use-apt-get-update-alone","pin-package-manager-versions-apt-get","pin-package-manager-versions-pip","pin-package-manager-versions-npm","pin-package-manager-versions-gem","pin-package-manager-versions-apk","use-copy-instead-of-add","use-wget-instead-of-add","do-not-have-secrets","have-a-healthcheck","have-a-user"],"successfullyFixedSmells":["use-no-install-recommends","have-a-healthcheck","have-a-user"],"processedDockerfile":"FROM 32bit/debian:jessie\n#   Install dependencies.  We start with the basic ones require to build protoc\n#   and the C++ build\nRUN apt-get update \\\n && apt-get install --no-install-recommends autoconf autotools-dev build-essential bzip2 ccache curl gcc git libc6 libc6-dbg libc6-dev libgtest-dev libtool make parallel time wget -y \\\n && apt-get clean\n#   Install php dependencies\nRUN apt-get clean \\\n && apt-get update \\\n && apt-get install --no-install-recommends bison php5 libcurl4-openssl-dev libssl-dev libxml2-dev unzip zlib1g-dev pkg-config -y --force-yes \\\n && apt-get clean\n#   Install other dependencies\nRUN wget http://ftp.gnu.org/gnu/bison/bison-2.6.4.tar.gz -O /var/local/bison-2.6.4.tar.gz\nRUN cd /var/local \\\n && tar -zxvf bison-2.6.4.tar.gz \\\n && cd /var/local/bison-2.6.4 \\\n && ./configure \\\n && make \\\n && make install\n#   Install composer\nRUN curl -sS https://getcomposer.org/installer | php\nRUN mv composer.phar /usr/local/bin/composer\n#   Download php source code\nRUN git clone https://github.com/php/php-src\n#   php 5.5\nRUN cd php-src \\\n && git checkout PHP-5.5.38 \\\n && ./buildconf --force\nRUN cd php-src \\\n && ./configure --enable-bcmath --with-openssl --with-zlib --prefix=/usr/local/php-5.5 \\\n && make \\\n && make install \\\n && make clean\nRUN cd php-src \\\n && ./configure --enable-maintainer-zts --with-openssl --with-zlib --prefix=/usr/local/php-5.5-zts \\\n && make \\\n && make install \\\n && make clean\nRUN wget -O phpunit https://phar.phpunit.de/phpunit-4.phar \\\n && chmod +x phpunit \\\n && cp phpunit /usr/local/php-5.5/bin \\\n && mv phpunit /usr/local/php-5.5-zts/bin\n#   php 5.6\nRUN cd php-src \\\n && git checkout PHP-5.6.39 \\\n && ./buildconf --force\nRUN cd php-src \\\n && ./configure --enable-bcmath --with-openssl --with-zlib --prefix=/usr/local/php-5.6 \\\n && make \\\n && make install \\\n && make clean\nRUN cd php-src \\\n && ./configure --enable-maintainer-zts --with-openssl --with-zlib --prefix=/usr/local/php-5.6-zts \\\n && make \\\n && make install \\\n && make clean\nRUN wget -O phpunit https://phar.phpunit.de/phpunit-5.phar \\\n && chmod +x phpunit \\\n && cp phpunit /usr/local/php-5.6/bin \\\n && mv phpunit /usr/local/php-5.6-zts/bin\n#   php 7.0\nRUN cd php-src \\\n && git checkout PHP-7.0.33 \\\n && ./buildconf --force\nRUN cd php-src \\\n && ./configure --enable-bcmath --with-openssl --with-zlib --prefix=/usr/local/php-7.0 \\\n && make \\\n && make install \\\n && make clean\nRUN cd php-src \\\n && ./configure --enable-maintainer-zts --with-openssl --with-zlib --prefix=/usr/local/php-7.0-zts \\\n && make \\\n && make install \\\n && make clean\nRUN wget -O phpunit https://phar.phpunit.de/phpunit-6.phar \\\n && chmod +x phpunit \\\n && cp phpunit /usr/local/php-7.0/bin \\\n && mv phpunit /usr/local/php-7.0-zts/bin\n#   php 7.1\nRUN cd php-src \\\n && git checkout PHP-7.1.25 \\\n && ./buildconf --force\nRUN cd php-src \\\n && ./configure --enable-bcmath --with-openssl --with-zlib --prefix=/usr/local/php-7.1 \\\n && make \\\n && make install \\\n && make clean\nRUN cd php-src \\\n && ./configure --enable-maintainer-zts --with-openssl --with-zlib --prefix=/usr/local/php-7.1-zts \\\n && make \\\n && make install \\\n && make clean\nRUN wget -O phpunit https://phar.phpunit.de/phpunit-7.phar \\\n && chmod +x phpunit \\\n && cp phpunit /usr/local/php-7.1/bin \\\n && mv phpunit /usr/local/php-7.1-zts/bin\n#   php 7.2\nRUN cd php-src \\\n && git checkout PHP-7.2.13 \\\n && ./buildconf --force\nRUN cd php-src \\\n && ./configure --enable-bcmath --with-openssl --with-zlib --prefix=/usr/local/php-7.2 \\\n && make \\\n && make install \\\n && make clean\nRUN cd php-src \\\n && ./configure --enable-maintainer-zts --with-openssl --with-zlib --prefix=/usr/local/php-7.2-zts \\\n && make \\\n && make install \\\n && make clean\nRUN wget -O phpunit https://phar.phpunit.de/phpunit-7.phar \\\n && chmod +x phpunit \\\n && cp phpunit /usr/local/php-7.2/bin \\\n && mv phpunit /usr/local/php-7.2-zts/bin\n#   php 7.3\nRUN cd php-src \\\n && git checkout PHP-7.3.0 \\\n && ./buildconf --force\nRUN cd php-src \\\n && ./configure --enable-bcmath --with-openssl --with-zlib --prefix=/usr/local/php-7.3 \\\n && make \\\n && make install \\\n && make clean\nRUN cd php-src \\\n && ./configure --enable-maintainer-zts --with-openssl --with-zlib --prefix=/usr/local/php-7.3-zts \\\n && make \\\n && make install \\\n && make clean\nRUN wget -O phpunit https://phar.phpunit.de/phpunit-7.phar \\\n && chmod +x phpunit \\\n && cp phpunit /usr/local/php-7.3/bin \\\n && mv phpunit /usr/local/php-7.3-zts/bin\n#   Install php dependencies\nRUN apt-get clean \\\n && apt-get update \\\n && apt-get install --no-install-recommends valgrind -y --force-yes \\\n && apt-get clean\nRUN groupadd --system docker-user ; useradd --system --gid docker-user docker-user\nUSER docker-user\n# Please add your HEALTHCHECK here!!!\n","originalDockerfile":"FROM 32bit/debian:jessie\n#  Install dependencies.  We start with the basic ones require to build protoc\n#  and the C++ build\nRUN apt-get update \\\n && apt-get install autoconf autotools-dev build-essential bzip2 ccache curl gcc git libc6 libc6-dbg libc6-dev libgtest-dev libtool make parallel time wget -y \\\n && apt-get clean\n#  Install php dependencies\nRUN apt-get clean \\\n && apt-get update \\\n && apt-get install bison php5 libcurl4-openssl-dev libssl-dev libxml2-dev unzip zlib1g-dev pkg-config -y --force-yes \\\n && apt-get clean\n#  Install other dependencies\nRUN wget http://ftp.gnu.org/gnu/bison/bison-2.6.4.tar.gz -O /var/local/bison-2.6.4.tar.gz\nRUN cd /var/local \\\n && tar -zxvf bison-2.6.4.tar.gz \\\n && cd /var/local/bison-2.6.4 \\\n && ./configure \\\n && make \\\n && make install\n#  Install composer\nRUN curl -sS https://getcomposer.org/installer | php\nRUN mv composer.phar /usr/local/bin/composer\n#  Download php source code\nRUN git clone https://github.com/php/php-src\n#  php 5.5\nRUN cd php-src \\\n && git checkout PHP-5.5.38 \\\n && ./buildconf --force\nRUN cd php-src \\\n && ./configure --enable-bcmath --with-openssl --with-zlib --prefix=/usr/local/php-5.5 \\\n && make \\\n && make install \\\n && make clean\nRUN cd php-src \\\n && ./configure --enable-maintainer-zts --with-openssl --with-zlib --prefix=/usr/local/php-5.5-zts \\\n && make \\\n && make install \\\n && make clean\nRUN wget -O phpunit https://phar.phpunit.de/phpunit-4.phar \\\n && chmod +x phpunit \\\n && cp phpunit /usr/local/php-5.5/bin \\\n && mv phpunit /usr/local/php-5.5-zts/bin\n#  php 5.6\nRUN cd php-src \\\n && git checkout PHP-5.6.39 \\\n && ./buildconf --force\nRUN cd php-src \\\n && ./configure --enable-bcmath --with-openssl --with-zlib --prefix=/usr/local/php-5.6 \\\n && make \\\n && make install \\\n && make clean\nRUN cd php-src \\\n && ./configure --enable-maintainer-zts --with-openssl --with-zlib --prefix=/usr/local/php-5.6-zts \\\n && make \\\n && make install \\\n && make clean\nRUN wget -O phpunit https://phar.phpunit.de/phpunit-5.phar \\\n && chmod +x phpunit \\\n && cp phpunit /usr/local/php-5.6/bin \\\n && mv phpunit /usr/local/php-5.6-zts/bin\n#  php 7.0\nRUN cd php-src \\\n && git checkout PHP-7.0.33 \\\n && ./buildconf --force\nRUN cd php-src \\\n && ./configure --enable-bcmath --with-openssl --with-zlib --prefix=/usr/local/php-7.0 \\\n && make \\\n && make install \\\n && make clean\nRUN cd php-src \\\n && ./configure --enable-maintainer-zts --with-openssl --with-zlib --prefix=/usr/local/php-7.0-zts \\\n && make \\\n && make install \\\n && make clean\nRUN wget -O phpunit https://phar.phpunit.de/phpunit-6.phar \\\n && chmod +x phpunit \\\n && cp phpunit /usr/local/php-7.0/bin \\\n && mv phpunit /usr/local/php-7.0-zts/bin\n#  php 7.1\nRUN cd php-src \\\n && git checkout PHP-7.1.25 \\\n && ./buildconf --force\nRUN cd php-src \\\n && ./configure --enable-bcmath --with-openssl --with-zlib --prefix=/usr/local/php-7.1 \\\n && make \\\n && make install \\\n && make clean\nRUN cd php-src \\\n && ./configure --enable-maintainer-zts --with-openssl --with-zlib --prefix=/usr/local/php-7.1-zts \\\n && make \\\n && make install \\\n && make clean\nRUN wget -O phpunit https://phar.phpunit.de/phpunit-7.phar \\\n && chmod +x phpunit \\\n && cp phpunit /usr/local/php-7.1/bin \\\n && mv phpunit /usr/local/php-7.1-zts/bin\n#  php 7.2\nRUN cd php-src \\\n && git checkout PHP-7.2.13 \\\n && ./buildconf --force\nRUN cd php-src \\\n && ./configure --enable-bcmath --with-openssl --with-zlib --prefix=/usr/local/php-7.2 \\\n && make \\\n && make install \\\n && make clean\nRUN cd php-src \\\n && ./configure --enable-maintainer-zts --with-openssl --with-zlib --prefix=/usr/local/php-7.2-zts \\\n && make \\\n && make install \\\n && make clean\nRUN wget -O phpunit https://phar.phpunit.de/phpunit-7.phar \\\n && chmod +x phpunit \\\n && cp phpunit /usr/local/php-7.2/bin \\\n && mv phpunit /usr/local/php-7.2-zts/bin\n#  php 7.3\nRUN cd php-src \\\n && git checkout PHP-7.3.0 \\\n && ./buildconf --force\nRUN cd php-src \\\n && ./configure --enable-bcmath --with-openssl --with-zlib --prefix=/usr/local/php-7.3 \\\n && make \\\n && make install \\\n && make clean\nRUN cd php-src \\\n && ./configure --enable-maintainer-zts --with-openssl --with-zlib --prefix=/usr/local/php-7.3-zts \\\n && make \\\n && make install \\\n && make clean\nRUN wget -O phpunit https://phar.phpunit.de/phpunit-7.phar \\\n && chmod +x phpunit \\\n && cp phpunit /usr/local/php-7.3/bin \\\n && mv phpunit /usr/local/php-7.3-zts/bin\n#  Install php dependencies\nRUN apt-get clean \\\n && apt-get update \\\n && apt-get install valgrind -y --force-yes \\\n && apt-get clean\n","injectedSmells":[],"originalDockerfileHash":"5c06b93be7081dc58001593545fdc20c","successfullyInjectedSmells":[],"originalDockerfileUglified":"FROM 32bit/debian:jessie\n#   Install dependencies.  We start with the basic ones require to build protoc\n#   and the C++ build\nRUN apt-get update \\\n && apt-get install autoconf autotools-dev build-essential bzip2 ccache curl gcc git libc6 libc6-dbg libc6-dev libgtest-dev libtool make parallel time wget -y \\\n && apt-get clean\n#   Install php dependencies\nRUN apt-get clean \\\n && apt-get update \\\n && apt-get install bison php5 libcurl4-openssl-dev libssl-dev libxml2-dev unzip zlib1g-dev pkg-config -y --force-yes \\\n && apt-get clean\n#   Install other dependencies\nRUN wget http://ftp.gnu.org/gnu/bison/bison-2.6.4.tar.gz -O /var/local/bison-2.6.4.tar.gz\nRUN cd /var/local \\\n && tar -zxvf bison-2.6.4.tar.gz \\\n && cd /var/local/bison-2.6.4 \\\n && ./configure \\\n && make \\\n && make install\n#   Install composer\nRUN curl -sS https://getcomposer.org/installer | php\nRUN mv composer.phar /usr/local/bin/composer\n#   Download php source code\nRUN git clone https://github.com/php/php-src\n#   php 5.5\nRUN cd php-src \\\n && git checkout PHP-5.5.38 \\\n && ./buildconf --force\nRUN cd php-src \\\n && ./configure --enable-bcmath --with-openssl --with-zlib --prefix=/usr/local/php-5.5 \\\n && make \\\n && make install \\\n && make clean\nRUN cd php-src \\\n && ./configure --enable-maintainer-zts --with-openssl --with-zlib --prefix=/usr/local/php-5.5-zts \\\n && make \\\n && make install \\\n && make clean\nRUN wget -O phpunit https://phar.phpunit.de/phpunit-4.phar \\\n && chmod +x phpunit \\\n && cp phpunit /usr/local/php-5.5/bin \\\n && mv phpunit /usr/local/php-5.5-zts/bin\n#   php 5.6\nRUN cd php-src \\\n && git checkout PHP-5.6.39 \\\n && ./buildconf --force\nRUN cd php-src \\\n && ./configure --enable-bcmath --with-openssl --with-zlib --prefix=/usr/local/php-5.6 \\\n && make \\\n && make install \\\n && make clean\nRUN cd php-src \\\n && ./configure --enable-maintainer-zts --with-openssl --with-zlib --prefix=/usr/local/php-5.6-zts \\\n && make \\\n && make install \\\n && make clean\nRUN wget -O phpunit https://phar.phpunit.de/phpunit-5.phar \\\n && chmod +x phpunit \\\n && cp phpunit /usr/local/php-5.6/bin \\\n && mv phpunit /usr/local/php-5.6-zts/bin\n#   php 7.0\nRUN cd php-src \\\n && git checkout PHP-7.0.33 \\\n && ./buildconf --force\nRUN cd php-src \\\n && ./configure --enable-bcmath --with-openssl --with-zlib --prefix=/usr/local/php-7.0 \\\n && make \\\n && make install \\\n && make clean\nRUN cd php-src \\\n && ./configure --enable-maintainer-zts --with-openssl --with-zlib --prefix=/usr/local/php-7.0-zts \\\n && make \\\n && make install \\\n && make clean\nRUN wget -O phpunit https://phar.phpunit.de/phpunit-6.phar \\\n && chmod +x phpunit \\\n && cp phpunit /usr/local/php-7.0/bin \\\n && mv phpunit /usr/local/php-7.0-zts/bin\n#   php 7.1\nRUN cd php-src \\\n && git checkout PHP-7.1.25 \\\n && ./buildconf --force\nRUN cd php-src \\\n && ./configure --enable-bcmath --with-openssl --with-zlib --prefix=/usr/local/php-7.1 \\\n && make \\\n && make install \\\n && make clean\nRUN cd php-src \\\n && ./configure --enable-maintainer-zts --with-openssl --with-zlib --prefix=/usr/local/php-7.1-zts \\\n && make \\\n && make install \\\n && make clean\nRUN wget -O phpunit https://phar.phpunit.de/phpunit-7.phar \\\n && chmod +x phpunit \\\n && cp phpunit /usr/local/php-7.1/bin \\\n && mv phpunit /usr/local/php-7.1-zts/bin\n#   php 7.2\nRUN cd php-src \\\n && git checkout PHP-7.2.13 \\\n && ./buildconf --force\nRUN cd php-src \\\n && ./configure --enable-bcmath --with-openssl --with-zlib --prefix=/usr/local/php-7.2 \\\n && make \\\n && make install \\\n && make clean\nRUN cd php-src \\\n && ./configure --enable-maintainer-zts --with-openssl --with-zlib --prefix=/usr/local/php-7.2-zts \\\n && make \\\n && make install \\\n && make clean\nRUN wget -O phpunit https://phar.phpunit.de/phpunit-7.phar \\\n && chmod +x phpunit \\\n && cp phpunit /usr/local/php-7.2/bin \\\n && mv phpunit /usr/local/php-7.2-zts/bin\n#   php 7.3\nRUN cd php-src \\\n && git checkout PHP-7.3.0 \\\n && ./buildconf --force\nRUN cd php-src \\\n && ./configure --enable-bcmath --with-openssl --with-zlib --prefix=/usr/local/php-7.3 \\\n && make \\\n && make install \\\n && make clean\nRUN cd php-src \\\n && ./configure --enable-maintainer-zts --with-openssl --with-zlib --prefix=/usr/local/php-7.3-zts \\\n && make \\\n && make install \\\n && make clean\nRUN wget -O phpunit https://phar.phpunit.de/phpunit-7.phar \\\n && chmod +x phpunit \\\n && cp phpunit /usr/local/php-7.3/bin \\\n && mv phpunit /usr/local/php-7.3-zts/bin\n#   Install php dependencies\nRUN apt-get clean \\\n && apt-get update \\\n && apt-get install valgrind -y --force-yes \\\n && apt-get clean\n","originalDockerfileUglifiedHash":"6772098f1ff0f8969de2a57e44c619a8","fileName":"/ICSME-replicationpackage/dataset/smelly_dockerfiles_bianncle/f8027c48e75c11da0ecace4f549ccf125ee1ebd2.dockerfile"}