{"seed":1696717969,"processedDockerfileHash":"e7acebdcea965ddc21e6ccbb81e73016","fixedSmells":["use-no-install-recommends","do-not-use-apt-get-update-alone","pin-package-manager-versions-apt-get","pin-package-manager-versions-pip","pin-package-manager-versions-npm","pin-package-manager-versions-gem","pin-package-manager-versions-apk","use-copy-instead-of-add","use-wget-instead-of-add","do-not-have-secrets","have-a-healthcheck","have-a-user"],"successfullyFixedSmells":["have-a-healthcheck","have-a-user"],"processedDockerfile":"FROM node:12-alpine\nLABEL maintainer=\"Vincenzo Chianese, vincenzo@express-gateway.io\"\nARG EG_VERSION=1.16.11\nRUN yarn global add express-gateway@$EG_VERSION \\\n && yarn cache clean\nENV NODE_ENV=\"production\"\nENV NODE_PATH=\"/usr/local/share/.config/yarn/global/node_modules/\"\nENV EG_CONFIG_DIR=\"/var/lib/eg\"\nENV CHOKIDAR_USEPOLLING=\"true\"\nVOLUME /var/lib/eg\nEXPOSE 8080/tcp 9876/tcp\nCOPY docker-entrypoint.sh /usr/local/bin/\nENTRYPOINT [\"docker-entrypoint.sh\"]\nCMD [\"node\", \"-e\", \"require\"]\nRUN addgroup -S docker-user ; adduser -S -G docker-user docker-user\nUSER docker-user\nHEALTHCHECK CMD curl --fail http://127.0.0.1:3000 || exit 1\n","originalDockerfile":"FROM node:12-alpine\n\nLABEL maintainer Vincenzo Chianese, vincenzo@express-gateway.io\n\nARG EG_VERSION=1.16.11\n\nRUN yarn global add express-gateway@$EG_VERSION && yarn cache clean\n\nENV NODE_ENV production\nENV NODE_PATH /usr/local/share/.config/yarn/global/node_modules/\nENV EG_CONFIG_DIR /var/lib/eg\n\nENV CHOKIDAR_USEPOLLING true\n\nVOLUME /var/lib/eg\n\nEXPOSE 8080 9876\n\nCOPY docker-entrypoint.sh /usr/local/bin/\nENTRYPOINT [\"docker-entrypoint.sh\"]\nCMD [\"node\", \"-e\", \"require('express-gateway')().run();\"]\n","injectedSmells":[],"originalDockerfileHash":"14ed438988198e0eb406e0a96521dc91","successfullyInjectedSmells":[],"originalDockerfileUglified":"FROM node:12-alpine\nLABEL maintainer=\"Vincenzo Chianese, vincenzo@express-gateway.io\"\nARG EG_VERSION=1.16.11\nRUN yarn global add express-gateway@$EG_VERSION \\\n && yarn cache clean\nENV NODE_ENV=\"production\"\nENV NODE_PATH=\"/usr/local/share/.config/yarn/global/node_modules/\"\nENV EG_CONFIG_DIR=\"/var/lib/eg\"\nENV CHOKIDAR_USEPOLLING=\"true\"\nVOLUME /var/lib/eg\nEXPOSE 8080/tcp 9876/tcp\nCOPY docker-entrypoint.sh /usr/local/bin/\nENTRYPOINT [\"docker-entrypoint.sh\"]\nCMD [\"node\", \"-e\", \"require\"]\n","originalDockerfileUglifiedHash":"93837fcb4629bc50a96319677ae70253","fileName":"/ICSME-replicationpackage/dataset/original_dockerfiles/express-gateway__1.x.dockerfile"}